odoo9_addon_project_task_materials-9.0.1.0.0-py2.7-nspkg.pth
odoo_addons/project_task_materials/__openerp__.py
odoo_addons/project_task_materials/__init__.py
odoo_addons/project_task_materials/README.rst
odoo_addons/project_task_materials/security/ir.model.access.csv
odoo_addons/project_task_materials/models/project.py
odoo_addons/project_task_materials/models/__init__.py
odoo_addons/project_task_materials/i18n/ja.po
odoo_addons/project_task_materials/i18n/lv.po
odoo_addons/project_task_materials/i18n/zh_CN.po
odoo_addons/project_task_materials/i18n/uk.po
odoo_addons/project_task_materials/i18n/es_AR.po
odoo_addons/project_task_materials/i18n/el.po
odoo_addons/project_task_materials/i18n/ko.po
odoo_addons/project_task_materials/i18n/gl_ES.po
odoo_addons/project_task_materials/i18n/pt.po
odoo_addons/project_task_materials/i18n/fr_CH.po
odoo_addons/project_task_materials/i18n/it.po
odoo_addons/project_task_materials/i18n/es.po
odoo_addons/project_task_materials/i18n/nl_BE.po
odoo_addons/project_task_materials/i18n/fr_FR.po
odoo_addons/project_task_materials/i18n/ar.po
odoo_addons/project_task_materials/i18n/lt.po
odoo_addons/project_task_materials/i18n/ro.po
odoo_addons/project_task_materials/i18n/tr.po
odoo_addons/project_task_materials/i18n/mk.po
odoo_addons/project_task_materials/i18n/hr.po
odoo_addons/project_task_materials/i18n/bg.po
odoo_addons/project_task_materials/i18n/es_EC.po
odoo_addons/project_task_materials/i18n/zh_TW.po
odoo_addons/project_task_materials/i18n/hu.po
odoo_addons/project_task_materials/i18n/gl.po
odoo_addons/project_task_materials/i18n/ca.po
odoo_addons/project_task_materials/i18n/es_CR.po
odoo_addons/project_task_materials/i18n/he.po
odoo_addons/project_task_materials/i18n/es_CO.po
odoo_addons/project_task_materials/i18n/sl.po
odoo_addons/project_task_materials/i18n/sr@latin.po
odoo_addons/project_task_materials/i18n/th.po
odoo_addons/project_task_materials/i18n/es_PE.po
odoo9_addon_project_task_materials-9.0.1.0.0.dist-info/top_level.txt
odoo9_addon_project_task_materials-9.0.1.0.0.dist-info/WHEEL
odoo9_addon_project_task_materials-9.0.1.0.0.dist-info/RECORD
odoo9_addon_project_task_materials-9.0.1.0.0.dist-info/metadata.json
odoo9_addon_project_task_materials-9.0.1.0.0.dist-info/DESCRIPTION.rst
odoo9_addon_project_task_materials-9.0.1.0.0.dist-info/METADATA
odoo9_addon_project_task_materials-9.0.1.0.0.dist-info/namespace_packages.txt
